goodtype/__init__.py
goodtype/main.py
goodtype-1.0.3.dist-info/LICENSE
goodtype-1.0.3.dist-info/METADATA
goodtype-1.0.3.dist-info/WHEEL
goodtype-1.0.3.dist-info/entry_points.txt
goodtype-1.0.3.dist-info/top_level.txt
goodtype-1.0.3.dist-info/RECORD
