Metadata-Version: 2.1
Name: goodtype
Version: 1.0.3
Summary: A simple static type checker for the python language, created for the ClusterF*** blog
Author-email: Prakhar Nagpal <thenextbigthingthidecade@gmail.com>
License: MIT License        
Project-URL: homepage, https://github.com/thenextbigthingthisdecade/goodtype
Project-URL: repository, https://github.com/thenextbigthingthisdecade/goodtype
Classifier: Environment :: Console
Classifier: Development Status :: 2 - Pre-Alpha
Classifier: Typing :: Typed
Requires-Python: >=3.6
License-File: LICENSE
